landspout/__init__.py
landspout/cli.py
landspout/core.py
landspout/modules.py
landspout-0.5.0.dist-info/METADATA
landspout-0.5.0.dist-info/RECORD
landspout-0.5.0.dist-info/WHEEL
landspout-0.5.0.dist-info/entry_points.txt
landspout-0.5.0.dist-info/top_level.txt
landspout-0.5.0.dist-info/zip-safe
