Metadata-Version: 2.1
Name: landspout
Version: 0.5.0
Summary: Static website generation tool
Home-page: https://github.com/gmr/landspout
Author: Gavin M. Roy
Author-email: gavinmroy@gmail.com
License: BSD
Keywords: static website generation
Platform: UNKNOWN
Classifier: Development Status :: 4 - Beta
Classifier: Intended Audience :: Developers
Classifier: Programming Language :: Python :: 3
Classifier: Programming Language :: Python :: 3.5
Classifier: Programming Language :: Python :: 3.6
Classifier: Programming Language :: Python :: 3.7
Classifier: License :: OSI Approved :: BSD License
Requires-Dist: pyyaml
Requires-Dist: tornado
